paquete_david_bautisa/__init__.py
paquete_david_bautisa/funciones.py
paquete_david_bautisa-0.0.1.dist-info/LICENSE
paquete_david_bautisa-0.0.1.dist-info/METADATA
paquete_david_bautisa-0.0.1.dist-info/WHEEL
paquete_david_bautisa-0.0.1.dist-info/top_level.txt
paquete_david_bautisa-0.0.1.dist-info/RECORD
