Metadata-Version: 2.1
Name: paquete-david-bautisa
Version: 0.0.1
Summary: Este es un paquete de prueba para subir a pypi   
Author-email: David Felipe Bautista <davidbautistab@usantotomas.edu.co>
License: MIT License        
Project-URL: Homepage, https://github.com/BautistaDavid/paquete_david_bautisa
Project-URL: Bug Tracker, https://github.com/BautistaDavid/paquete_david_bautisa/issues
Classifier: Programming Language :: Python :: 3
Classifier: License :: OSI Approved :: MIT License
Classifier: Operating System :: OS Independent
Requires-Python: >=3.7
License-File: LICENSE
